rf19is/__init__.py
rf19is-0.0.5.dist-info/LICENSE.txt
rf19is-0.0.5.dist-info/METADATA
rf19is-0.0.5.dist-info/WHEEL
rf19is-0.0.5.dist-info/top_level.txt
rf19is-0.0.5.dist-info/RECORD
