Metadata-Version: 2.1
Name: rf19is
Version: 0.0.5
Summary: For AI/Ml Lab
Home-page: UNKNOWN
Author: Phil Dunphy (And Luke)
Author-email: <mail@neuralnine.com>
License: UNKNOWN
Keywords: python,video,stream,video stream,camera stream,sockets
Platform: UNKNOWN
Classifier: Development Status :: 1 - Planning
Classifier: Intended Audience :: Developers
Classifier: Programming Language :: Python :: 3
Classifier: Operating System :: Unix
Classifier: Operating System :: MacOS :: MacOS X
Classifier: Operating System :: Microsoft :: Windows
License-File: LICENSE.txt
Requires-Dist: pyperclip
